pytorch_kerosene/__init__.py
pytorch_kerosene/hparam_optim.py
pytorch_kerosene/trainer.py
pytorch_kerosene/utils/__init__.py
pytorch_kerosene/utils/logger.py
pytorch_kerosene/utils/metrics.py
pytorch_kerosene/utils/utils.py
pytorch_kerosene-0.2.2.dist-info/LICENSE
pytorch_kerosene-0.2.2.dist-info/METADATA
pytorch_kerosene-0.2.2.dist-info/WHEEL
pytorch_kerosene-0.2.2.dist-info/top_level.txt
pytorch_kerosene-0.2.2.dist-info/RECORD
