Metadata-Version: 2.1
Name: pytorch-kerosene
Version: 0.2.2
Summary: PyTorch Kerosene is a tool for abstracting the training process of PyTorch models.
Author: Silvan Ferreira
Author-email: silvanfj@gmail.com
Keywords: python,pytorch
Classifier: Programming Language :: Python :: 3
Classifier: License :: OSI Approved :: MIT License
Classifier: Operating System :: OS Independent
License-File: LICENSE
